flattree/__init__.py
flattree/api.py
flattree/logic.py
tests/__init__.py
tests/conftest.py
tests/test_api.py
tests/test_logic.py
flattree-2.0.2.dist-info/LICENSE
flattree-2.0.2.dist-info/METADATA
flattree-2.0.2.dist-info/WHEEL
flattree-2.0.2.dist-info/top_level.txt
flattree-2.0.2.dist-info/RECORD
