Metadata-Version: 2.1
Name: flattree
Version: 2.0.2
Summary: FlatTree is a tool to work with nested Python dictionaries.
Home-page: https://github.com/flattree/flattree
Author: Aleksandr Mikhailov
Author-email: dev@avidclam.com
License: MIT
Platform: UNKNOWN
Classifier: Programming Language :: Python :: 3.6
Classifier: License :: OSI Approved :: MIT License
Classifier: Development Status :: 4 - Beta
Classifier: Intended Audience :: Developers
Classifier: Topic :: Software Development :: Libraries :: Python Modules
Requires-Python: >=3.6.8
